FritzHome/__init__.py
robotframework_fritzhomelibrary-1.3.0.dist-info/LICENSE
robotframework_fritzhomelibrary-1.3.0.dist-info/METADATA
robotframework_fritzhomelibrary-1.3.0.dist-info/WHEEL
robotframework_fritzhomelibrary-1.3.0.dist-info/top_level.txt
robotframework_fritzhomelibrary-1.3.0.dist-info/RECORD
