Metadata-Version: 2.1
Name: robotframework-fritzhomelibrary
Version: 1.3.0
Summary: Access to AVM Home Automation with Robot Framework
Home-page: https://github.com/oeick/robotframework-fritzhomelibrary
Author: Oliver Eickmeyer
Author-email: oliver.eickmeyer@gmail.com
License: UNKNOWN
Keywords: robotframework testing homeautomation fritzbox
Platform: UNKNOWN
Classifier: Programming Language :: Python :: 3
Classifier: License :: OSI Approved :: MIT License
Classifier: Operating System :: OS Independent
Requires-Dist: robotframework (>=3.1.0)
Requires-Dist: requests (>=2.21.0)
